rescan/__init__.py
rescan/__main__.py
rescan/rescan.py
rescan-1.0.4.data/data/README.md
rescan-1.0.4.data/scripts/rescan
rescan-1.0.4.dist-info/LICENSE
rescan-1.0.4.dist-info/METADATA
rescan-1.0.4.dist-info/WHEEL
rescan-1.0.4.dist-info/entry_points.txt
rescan-1.0.4.dist-info/top_level.txt
rescan-1.0.4.dist-info/RECORD
